setup.py
platformer/__init__.py
platformer/cbuild.py
platformer/darwin.py
platformer/distutils_platform.py
platformer/freebsd.py
platformer/linux.py
platformer/maemo.py
platformer/openbsd.py
platformer/posix.py
platformer/runsubprocess.py
platformer/stdoutcapture.py
platformer/windows.py
platformer.egg-info/PKG-INFO
platformer.egg-info/SOURCES.txt
platformer.egg-info/dependency_links.txt
platformer.egg-info/requires.txt
platformer.egg-info/top_level.txt
platformer.egg-info/zip-safe