Metadata-Version: 1.0
Name: platformer
Version: 1.0-dev
Summary: A cross-platform way to compile and run C files
Home-page: http://github.com/fijal/platformer
Author: The PyPy team, maintained by Maciej Fijałkowski
Author-email: fijall@gmail.com
License: UNKNOWN
Platform: UNKNOWN
